{
	"Class": "DateUtils",
	"FullPath": "regesta.regestalibrary.utilities.DateUtils",
	"Description": "Utility class for dates manipulation",
	"Attributes": [],
	"Methods": [{
		"Name": "addTime",
		"Description": "Adds time (of specified unit of measure) to date",
		"Parameters": [{
			"Name": "date",
			"Type": "date",
			"Default": null,
			"Description": "Date to which add time",
			"Optional": false,
			"Level": 1
		}, {
			"Name": "time",
			"Type": "integer",
			"Default": null,
			"Description": "Amount of time to be added (either positive or negative)",
			"Optional": false,
			"Level": 1
		}, {
			"Name": "uom",
			"Type": "regesta.regestalibrary.enum.timeUoms",
			"Default": null,
			"Description": "Unit of measure of the time to be added",
			"Optional": false,
			"Level": 1
		}],
		"ReturnType": "date"
	},
	{
		"Name": "addWorkingDays",
		"Description": "Adds number of working days to a date",
		"Parameters": [{
			"Name": "startDate",
			"Type": "date",
			"Default": null,
			"Description": "Date to which add time",
			"Optional": false,
			"Level": 1
		}, {
			"Name": "days",
			"Type": "integer",
			"Default": null,
			"Description": "Amount of working days to be added (only positive values)",
			"Optional": false,
			"Level": 1
		}],
		"ReturnType": "date"
	}]
}